find_unicode_executable.py
find_unicode_executable-0.1.0a2.dist-info/licenses/LICENSE
find_unicode_executable-0.1.0a2.dist-info/METADATA
find_unicode_executable-0.1.0a2.dist-info/WHEEL
find_unicode_executable-0.1.0a2.dist-info/top_level.txt
find_unicode_executable-0.1.0a2.dist-info/RECORD
