Metadata-Version: 2.4
Name: find-unicode-executable
Version: 0.1.0a2
Summary: A Python package that provides cross-platform Unicode executable path resolution. Like Unix `which` command but better.
Author-email: Jifeng Wu <jifengwu2k@gmail.com>
License-Expression: MIT
Project-URL: Homepage, https://github.com/jifengwu2k/find-unicode-executable
Project-URL: Bug Tracker, https://github.com/jifengwu2k/find-unicode-executable/issues
Classifier: Programming Language :: Python :: 2
Classifier: Programming Language :: Python :: 3
Classifier: Operating System :: OS Independent
Requires-Python: >=2
License-File: LICENSE
Requires-Dist: posix-or-nt
Requires-Dist: read-unicode-environment-variables-dictionary
Requires-Dist: typing; python_version < "3.5"
Dynamic: license-file
